goats/__init__.py
goats/core/__init__.py
goats/core/algebraic.py
goats/core/aliased.py
goats/core/axis.py
goats/core/computed.py
goats/core/constant.py
goats/core/datafile.py
goats/core/fundamental.py
goats/core/index.py
goats/core/interpolation.py
goats/core/iotools.py
goats/core/iterables.py
goats/core/measurable.py
goats/core/metadata.py
goats/core/metric.py
goats/core/numerical.py
goats/core/observed.py
goats/core/observer.py
goats/core/observing.py
goats/core/operational.py
goats/core/physical.py
goats/core/plasma.py
goats/core/reference.py
goats/core/spelling.py
goats/core/symbolic.py
goats/core/utilities.py
goats/core/variable.py
goats/eprem/__init__.py
goats/eprem/runtime.json
goats/eprem/runtime.py
goats-0.2.7.dist-info/LICENSE
goats-0.2.7.dist-info/WHEEL
goats-0.2.7.dist-info/METADATA
goats-0.2.7.dist-info/RECORD
