Metadata-Version: 2.1
Name: goats
Version: 0.2.7
Summary: A set of tools for analyzing heliophysical datasets
License: GNU General Public License v3.0
Author: Matt Young
Requires-Python: >=3.8,<3.11
Classifier: License :: Other/Proprietary License
Classifier: Programming Language :: Python :: 3
Classifier: Programming Language :: Python :: 3.10
Classifier: Programming Language :: Python :: 3.8
Classifier: Programming Language :: Python :: 3.9
Requires-Dist: matplotlib (>=3.5.1,<4.0.0)
Requires-Dist: netCDF4 (>=1.5.8,<2.0.0)
Requires-Dist: numpy (>=1.21.4,<1.23)
Requires-Dist: scipy (>=1.7.3,<2.0.0)
